<annotation>
	<folder>my-project-name</folder>
	<filename>istockphoto-624126004-612x612.jpg</filename>
	<path>/my-project-name/istockphoto-624126004-612x612.jpg</path>
	<source>
		<database>Unspecified</database>
	</source>
	<size>
		<width>612</width>
		<height>408</height>
		<depth>3</depth>
	</size>
	<object>
		<name>pig</name>
		<pose>Unspecified</pose>
		<truncated>0</truncated>
		<difficult>0</difficult>
		<bndbox>
			<xmin>29</xmin>
			<ymin>73</ymin>
			<xmax>358</xmax>
			<ymax>289</ymax>
		</bndbox>
	</object>
</annotation>